sorna_common-0.9.6-py3.6-nspkg.pth
sorna/argparse.py
sorna/defs.py
sorna/exceptions.py
sorna/logging.py
sorna/monitor.py
sorna/utils.py
sorna/proto/__init__.py
sorna/proto/msgtypes.py
sorna/proto/serialize.py
sorna_common-0.9.6.dist-info/DESCRIPTION.rst
sorna_common-0.9.6.dist-info/METADATA
sorna_common-0.9.6.dist-info/RECORD
sorna_common-0.9.6.dist-info/WHEEL
sorna_common-0.9.6.dist-info/metadata.json
sorna_common-0.9.6.dist-info/namespace_packages.txt
sorna_common-0.9.6.dist-info/top_level.txt
